{
	"files": [

	],
	"folders": {
		"Characters": {
			"files": [
				"character-1637178929.json",
				"character-1637179615.json"
			],
			"folders": {

			},
			"metadata": {
				"color": null,
				"folded": false
			}
		},
		"Definitions": {
			"files": [

			],
			"folders": {

			},
			"metadata": {
				"color": null,
				"folded": false
			}
		},
		"Themes": {
			"files": [
				"theme-1637180499.cfg"
			],
			"folders": {

			},
			"metadata": {
				"color": null,
				"folded": false
			}
		},
		"Timelines": {
			"files": [
				"timeline-1637180008.json"
			],
			"folders": {

			},
			"metadata": {
				"color": null,
				"folded": false
			}
		}
	}
}
